main.py
source_jina_ai_reader/__init__.py
source_jina_ai_reader/components.py
source_jina_ai_reader/config_migration.py
source_jina_ai_reader/manifest.yaml
source_jina_ai_reader/run.py
source_jina_ai_reader/source.py
airbyte_source_jina_ai_reader-0.1.40.dist-info/METADATA
airbyte_source_jina_ai_reader-0.1.40.dist-info/WHEEL
airbyte_source_jina_ai_reader-0.1.40.dist-info/entry_points.txt
airbyte_source_jina_ai_reader-0.1.40.dist-info/RECORD
