Metadata-Version: 2.3
Name: airbyte-source-jina-ai-reader
Version: 0.1.40
Summary: Source implementation for jina-ai-reader.
License: MIT
Author: Airbyte
Author-email: contact@airbyte.io
Requires-Python: >=3.9,<3.12
Classifier: License :: OSI Approved :: MIT License
Classifier: Programming Language :: Python :: 3
Classifier: Programming Language :: Python :: 3.9
Classifier: Programming Language :: Python :: 3.10
Classifier: Programming Language :: Python :: 3.11
Requires-Dist: airbyte-cdk (>=1,<2)
Project-URL: Documentation, https://docs.airbyte.com/integrations/sources/jina-ai-reader
Project-URL: Homepage, https://airbyte.com
Project-URL: Repository, https://github.com/airbytehq/airbyte
